forge_template/__init__.py
forge_template/__main__.py
forge_template/actions.py
forge_template/config_generator.py
forge_template/constants.py
forge_template/exception/__init__.py
forge_template/exception/exceptions.py
forge_template/exception/handler.py
forge_template/handler/__init__.py
forge_template/handler/azure_handler.py
forge_template/handler/databricks_handler.py
forge_template/handler/git_utils.py
forge_template/handler/github_actions_handler.py
forge_template/handler/handler.py
forge_template/handler/powerbi_handler.py
forge_template/handler/sa_file_handler.py
forge_template/main.py
forge_template/paths.py
forge_template/sa_actions.py
forge_template/sa_constants.py
forge_template/schema/config_schema.yaml
forge_template/schema/job_config_schema.yaml
forge_template/schema/project_config_schema.yaml
forge_template/schema/schedule_config_schema.yaml
forge_template/schema/secrets_schema.yaml
forge_template/templates/data_replicator/custom_replicator/schedule_config_file_template.txt
forge_template/templates/data_replicator/extractor_workflow/job_config_file_template.yaml
forge_template/templates/data_replicator/extractor_workflow/schedule_config_file_template.txt
forge_template/templates/databricks/jobs/powerbi-dataset-refresh.py
forge_template/templates/databricks/notebooks/sample-spark-model.py
forge_template/templates/databricks/setup/basemodel.py
forge_template/templates/databricks/setup/setup-environment.py
forge_template/templates/github_workflows/deploy_databricks.yaml
forge_template/templates/github_workflows/deploy_powerbi.yaml
forge_template/templates/infra_scripts/deploy_databricks.py
forge_template/templates/infra_scripts/deploy_powerbi.py
forge_template/templates/pipelines/databricks.yml
forge_template/templates/pipelines/powerbi.yml
forge_template/templates/powerbi/datasets/base_dataset.pbix
forge_template/templates/powerbi/reports/base_report.pbix
forge_template/tool_info.py
forge_template/user_interface.py
forge_template/util/__init__.py
cognite_forge_template-0.11.0.dist-info/entry_points.txt
cognite_forge_template-0.11.0.dist-info/LICENSE
cognite_forge_template-0.11.0.dist-info/WHEEL
cognite_forge_template-0.11.0.dist-info/METADATA
cognite_forge_template-0.11.0.dist-info/RECORD
