Metadata-Version: 2.1
Name: cognite-forge-template
Version: 0.11.0
Summary: Automation of software used for data science in Cognite, including Databricks, PowerBI, Git and Grafana
Author: Magnus Moan
Author-email: magnus.moan@cognite.com
Requires-Python: >=3.6,<4.0
Classifier: Programming Language :: Python :: 3
Classifier: Programming Language :: Python :: 3.6
Classifier: Programming Language :: Python :: 3.7
Classifier: Programming Language :: Python :: 3.8
Classifier: Programming Language :: Python :: 3.9
Requires-Dist: cerberus (>=1.3,<2.0)
Requires-Dist: click (>=7.0,<8.0)
Requires-Dist: cognite-sdk (>=1.8.0,<2.0.0)
Requires-Dist: colorama (==0.4.1)
Requires-Dist: databricks-api (>=0.3.0,<0.4.0)
Requires-Dist: google-cloud-secret-manager (==2.0.0)
Requires-Dist: google-cloud-storage (>=1.28.0,<2.0.0)
Requires-Dist: jinja2 (>=2.11.2,<3.0.0)
Requires-Dist: pyfiglet (>=0.8.post1,<0.9)
Requires-Dist: pytest-lazy-fixture (>=0.6.3,<0.7.0)
Requires-Dist: requests (>=2.22,<3.0)
Requires-Dist: ruamel.yaml (>=0.16.5,<0.17.0)
Requires-Dist: termcolor (>=1.1.0,<2.0.0)
Requires-Dist: toml (>=0.10.0,<0.11.0)
